wield/utilities/__init__.py
wield/utilities/_version.py
wield/utilities/args.py
wield/utilities/np.py
wield/utilities/pprint.py
wield/utilities/strings.py
wield/utilities/arguments/__init__.py
wield/utilities/arguments/aid.py
wield/utilities/arguments/base.py
wield/utilities/arguments/logging.py
wield/utilities/arguments/pyargparse.py
wield/utilities/check_versions/__init__.py
wield/utilities/check_versions/__main__.py
wield/utilities/file_io/__init__.py
wield/utilities/file_io/any_io.py
wield/utilities/file_io/csv_io.py
wield/utilities/file_io/hdf5_io.py
wield/utilities/file_io/ini_io.py
wield/utilities/file_io/json_io.py
wield/utilities/file_io/matlab_io.py
wield/utilities/file_io/pickle_io.py
wield/utilities/file_io/types.py
wield/utilities/file_io/utilities.py
wield/utilities/file_io/yaml_io.py
wield/utilities/ipynb/__init__.py
wield/utilities/ipynb/displays.py
wield/utilities/ipynb/sympy.py
wield/utilities/mpl/__init__.py
wield/utilities/mpl/autoniceplot.py
wield/utilities/mpl/colors.py
wield/utilities/mpl/logticks.py
wield/utilities/mpl/stacked_plots.py
wield/utilities/mpl/utils.py
wield/utilities/priority_queue/__init__.py
wield.utilities-0.9.9.dist-info/Apache-2.0.txt
wield.utilities-0.9.9.dist-info/CC0-1.0.txt
wield.utilities-0.9.9.dist-info/METADATA
wield.utilities-0.9.9.dist-info/NOTICE
wield.utilities-0.9.9.dist-info/WHEEL
wield.utilities-0.9.9.dist-info/top_level.txt
wield.utilities-0.9.9.dist-info/RECORD
