Metadata-Version: 2.1
Name: wield.utilities
Version: 0.9.9
Summary: utilities for testing, string, numpy, file io, and matplotlib conveniences
Home-page: https://github.com/wieldphysics/wield-utilities
Author: Lee McCuller
Author-email: mcculler@caltech.edu
License: Apache-2.0
Project-URL: Bug Tracker, https://github.com/wieldphysics/wield-utilities/issues
Project-URL: Source Code, https://github.com/wieldphysics/wield-utilities
Classifier: Intended Audience :: Science/Research
Classifier: License :: OSI Approved :: Apache Software License
Classifier: Operating System :: OS Independent
Classifier: Programming Language :: Python
Classifier: Programming Language :: Python :: 3
Classifier: Topic :: Scientific/Engineering :: Physics
License-File: LICENSES/Apache-2.0.txt
License-File: LICENSES/CC0-1.0.txt
License-File: NOTICE
Requires-Dist: setuptools-scm (>=6.0.0)
Requires-Dist: wield.bunch
